ml_pipeline/__init__.py
ml_pipeline/app.py
ml_pipeline/eda.py
ml_pipeline/model.py
ml_pipeline/preprocessing.py
MLPipelineProject-0.1.3.dist-info/LICENSE
MLPipelineProject-0.1.3.dist-info/METADATA
MLPipelineProject-0.1.3.dist-info/WHEEL
MLPipelineProject-0.1.3.dist-info/entry_points.txt
MLPipelineProject-0.1.3.dist-info/top_level.txt
MLPipelineProject-0.1.3.dist-info/RECORD
