Metadata-Version: 2.1
Name: MLPipelineProject
Version: 0.1.3
Summary: A package for EDA with Streamlit dashboard
Author: Jhansi Siriprolu
Author-email: siriprolu2018@gmail.com
Classifier: Programming Language :: Python :: 3
Classifier: License :: OSI Approved :: MIT License
License-File: LICENSE
Requires-Dist: streamlit
Requires-Dist: pandas
Requires-Dist: numpy
Requires-Dist: scikit-learn
Requires-Dist: seaborn
Requires-Dist: matplotlib
Requires-Dist: xgboost
